MANIFEST.in
README.rst
setup.py
baidufm/__init__.py
baidufm/baidufm.py
baidufm/c_image.py
baidufm/consts.py
baidufm/fm_api.py
baidufm/fm_cli.py
baidufm/fm_footer.py
baidufm/fm_player.py
baidufm/fm_utils.py
baidufm/image.c
baidufm/logs.py
baidufm.egg-info/PKG-INFO
baidufm.egg-info/SOURCES.txt
baidufm.egg-info/dependency_links.txt
baidufm.egg-info/entry_points.txt
baidufm.egg-info/requires.txt
baidufm.egg-info/top_level.txt