Metadata-Version: 1.0
Name: baidufm
Version: 0.2.5
Summary: BaiduFm cli python
Home-page: https://github.com/tdoly/baidufm-py
Author: tdoly
Author-email: hi@tdoly.com
License: MIT
Keywords: baidufm,baidufm-py,baidufm cli
Platform: Any
